{
  "paperType": "real",
  "subjectId": "03",
  "name": "2025年12月真题",
  "fullName": "长期保险",
  "title": "卷三：2025年12月真题",
  "questionCount": 85,
  "durationMinutes": 120,
  "questions": [
    {
      "id": "q1",
      "type": "single",
      "content": "就最高誠信原則，在免體檢的投保的前題下，以下哪項不屬違反最高誠信的情況?",
      "options": {
        "A": "沒有披露未被驗出的腦瘤",
        "B": "沒有披露近日收到高利貸債主的死亡恐嚇",
        "C": "隱瞞自己從驗身得知的癌症",
        "D": "隱瞞自己意外導致嚴重受傷"
      },
      "correctAnswer": "A",
      "explanation": "有些疾病對合資格醫生而言可能很容\n易察覺，但是不能期望一般人也能夠\n進行自我診斷並作披露。",
      "score": 10
    },
    {
      "id": "q2",
      "type": "single",
      "content": "人壽保險費率的均衡保費制度是指在保險期內，每年所繳的保費相同， 並假設:",
      "options": {
        "A": "利率沒有大幅度下降",
        "B": "死亡保險金維持不變",
        "C": "經濟環境保持合理平穩",
        "D": "保險人的賠償經驗仍可接受的"
      },
      "correctAnswer": "B",
      "explanation": "人壽保險費率的均衡保費制度是指在\n保險期內，保費不變，同時死亡保險\n金亦維持不變。",
      "score": 10
    },
    {
      "id": "q3",
      "type": "single",
      "content": "下列哪項屬於自然保費制度的特點？",
      "options": {
        "A": "保費隨年齡增長而增加",
        "B": "會產生逆選擇",
        "C": "大部份保險公司已不採用",
        "D": "以上各項皆正確"
      },
      "correctAnswer": "D",
      "explanation": "以上各項都屬於自然保費制度的特點",
      "score": 10
    },
    {
      "id": "q4",
      "type": "single",
      "content": "以下哪項關於死亡表的描述是正確的?\ni.\t 顯示不同年齡的預期死亡比率的計算表\nii.\t 應付所有預期及可能出現的營運開支\niii.\t 考慮某種新疾病或其他災難引起異常死亡率的可能性\niv.\t 只應付正常風險和正常預期的死亡率",
      "options": {
        "A": "i, iii",
        "B": "i,iv",
        "C": "ii,iv",
        "D": "以上各項皆是"
      },
      "correctAnswer": "B",
      "explanation": "死亡表或稱生命表顯示不同年齡的預\n期死亡比率的計算表，在保險行業中\n十分通用。利用死亡表釐定費率，只\n是應付正常風險和正常預期。所以只\n有選項i及iv是正確",
      "score": 10
    },
    {
      "id": "q5",
      "type": "single",
      "content": "在人壽保險中，只有在合約開始時才需要可保權益，以下哪項情況會出現有效索償?",
      "options": {
        "A": "夫妻於離婚前，為其配偶的生命購買人壽保單",
        "B": "債務清還前，就債務人的生命購買人壽保單",
        "C": "關鍵人物人壽保單，受保僱於保單起保數天後離職",
        "D": "以上各項例子"
      },
      "correctAnswer": "D",
      "explanation": "人壽保險的可保權益只有在合約開始\n時才需要，就以上的關係轉變，仍然\n維持該保單的有效性",
      "score": 10
    },
    {
      "id": "q7",
      "type": "single",
      "content": "下列哪項肯定屬於投保人必須披露的重要事實:",
      "options": {
        "A": "與實質物件(財產)的保險有關的事實",
        "B": "會影響一名審慎的保險人訂定保費或決定是否承擔風險方面判斷的事實",
        "C": "可能影響一名審慎的核保人就一項特定風險釐定保費的判斷的事實",
        "D": "被保險人向保險人披露的重要事實"
      },
      "correctAnswer": "B",
      "explanation": "重要事實是會影響一名審慎的保險人\n訂定保費或決定是否承擔風險方面判\n斷的事實",
      "score": 10
    },
    {
      "id": "q8",
      "type": "single",
      "content": "以下哪項為最高誠信的正確描述？\ni.\t 就某些不可異議條文，保險人不得在保單生效了一段時訂明時間內對該份保單提出異議或質疑\nii.\t 就免體檢的投保，一份小心設計的投保單是很重要\niii.\t 在不構成欺詐的情況下，若受保生命違反最高誠信在可異議期間後才可獲得寬宥\niv.\t 要求投保人披露所有重要事實，不管保險人有沒有提出要求",
      "options": {
        "A": "ii,iii,iv",
        "B": "i,ii,iv",
        "C": "i,ii",
        "D": "iii,iv"
      },
      "correctAnswer": "D",
      "explanation": "就不可異議條文，保險人可以在保單\n生效了的兩年內對該份保單提出異議\n或質疑，就免體檢的投保，一份小心\n設計的投保單未必很重要",
      "score": 10
    },
    {
      "id": "q9",
      "type": "single",
      "content": "人壽保險最初的目的為：",
      "options": {
        "A": "為退休後支付每個月的生活費",
        "B": "向被保險人的家屬提供幫助",
        "C": "為一名海上死亡的船員提供保障",
        "D": "應付短期債務之用"
      },
      "correctAnswer": "A",
      "explanation": "人壽保險的最初及最基本目的是，\n在被保險人或稱受保人去世後，尤其\n在早逝的情況下，很大可能會給受養\n人帶來經濟困難，人壽保險利益可向\n被保險人的家人或其他人提供幫助。 B\n10  1.1\n人壽保險最初及最基本的目的，在現代社會也有這樣的保障保險(定期壽險)是什麼？\na)死亡(尤其在早逝的情況下)\nb)為受保人在生的每一年提供生活收入\nc)儲蓄\nd)在餘下生命裏提供保障\n最初，保險單有效期較短，只為暫時\n性的風險情況",
      "score": 10
    },
    {
      "id": "q11",
      "type": "single",
      "content": "按照壽險傳統保費計算方法，保費應該可應付所有有關成本，並可反映有關之風險，描述有關之保\n費標準為：",
      "options": {
        "A": "公平及公正的",
        "B": "公平及足夠的",
        "C": "充足及公平（公正）的",
        "D": "充足及合適的"
      },
      "correctAnswer": "C",
      "explanation": "按照壽險傳統保費計算方法有關之保\n費標準為充足及公平（公正）的",
      "score": 10
    },
    {
      "id": "q12",
      "type": "single",
      "content": "在人壽保險保費的一般計算中，在正常統計預期下足夠支付死亡索償所需，向保單所有人收取的金\n額是以下哪一種保費：",
      "options": {
        "A": "實收保費",
        "B": "淨保費（純保險費）",
        "C": "毛保費",
        "D": "充足及公平的保費"
      },
      "correctAnswer": "B",
      "explanation": "在正常統計預期下足夠支付死亡索償\n所需向保單所有人收取的金額是淨保\n費（又叫純保險費）",
      "score": 10
    },
    {
      "id": "q1",
      "type": "single",
      "content": "i)\n可作為保單抵押貸款的抵押物是：",
      "options": {
        "A": "銀行中的存款",
        "B": "保單的現金價值",
        "C": "保單所有人所持有的財產",
        "D": "以上各項都是"
      },
      "correctAnswer": "B",
      "explanation": "可作為保單抵押貸款的抵押物是保單\n的現金價值",
      "score": 10
    },
    {
      "id": "q14",
      "type": "single",
      "content": "相比於終身壽險及儲蓄壽險，以下哪項有關定期壽險的描述是正確的？",
      "options": {
        "A": "保費是最便宜的",
        "B": "大多數情況下，在保單到期時仍未出現索償",
        "C": "只提供短暫的保障",
        "D": "上述所有各項"
      },
      "correctAnswer": "D",
      "explanation": "上述所有各項都是定期壽險的正確的\n描述",
      "score": 10
    },
    {
      "id": "q15",
      "type": "single",
      "content": "下列哪項屬於基本形式之壽險保單的常見變化？\ni)保單所有人可以選擇將保單紅利轉換為公司股份\nii)如果最初只投保一段有限時間，可能可以續保\niii)保單所有人可以選擇將保單紅利轉換為公司優先股\niv)保單可加入各種附約，用以改善所提供的保障",
      "options": {
        "A": "i, ii",
        "B": "iii, iv",
        "C": "ii, iv",
        "D": "i, ii, iii, iv"
      },
      "correctAnswer": "C",
      "explanation": "可續保的及可轉換的是人壽保險的基\n本變數",
      "score": 10
    },
    {
      "id": "q16",
      "type": "single",
      "content": "就可續保定期壽險而言，以下哪一個說法不正確?",
      "options": {
        "A": "保費將會隨受保生命的年齡的增長而增加",
        "B": "新保費是按照到達年齡來計算",
        "C": "續保的權利已存在毋須提交可保性證明",
        "D": "以上各項皆不是"
      },
      "correctAnswer": "D",
      "explanation": "因為以上各項皆是可續保定期壽險的\n正確描述，所以答案D是正確答案。",
      "score": 10
    },
    {
      "id": "q17",
      "type": "single",
      "content": "儲蓄壽險在香港並不流行，你認為原因何在？",
      "options": {
        "A": "佣金率比較低",
        "B": "對於投保的普羅大眾，這種壽險一般較難了解",
        "C": "它比較貴",
        "D": "其實儲蓄壽險比定期壽險和終身壽險更流行"
      },
      "correctAnswer": "C",
      "explanation": "儲蓄壽險在香港並不流行，因為保費\n較貴，這是跟實務知識不相同。",
      "score": 10
    },
    {
      "id": "q18",
      "type": "single",
      "content": "萬用壽險增加或減少保額:",
      "options": {
        "A": "必需提交可保性證明",
        "B": "如增加保額，需提供可保性證明",
        "C": "如減少保額，需提供可保性證明",
        "D": "如增加保額後第二年後提出索償，該次索償則屬無效"
      },
      "correctAnswer": "B",
      "explanation": "萬用壽險如增加保額，需提供可保性\n證明",
      "score": 10
    },
    {
      "id": "q19",
      "type": "single",
      "content": "在_________內，保單持有人在一段時間內定期繳付保費，讓保險人通過投資令已付金額增長。",
      "options": {
        "A": "累積期",
        "B": "延遲時間",
        "C": "年金期",
        "D": "以上各項皆不是"
      },
      "correctAnswer": "A",
      "explanation": "延期年金計劃在累積期內，保單持有\n人在一段時間內定期繳付保費，讓保\n險人通過投資令已付金額增長",
      "score": 10
    },
    {
      "id": "q20",
      "type": "single",
      "content": "合資格延期年金保費容許夫婦合共申請扣除總額上限是多少?",
      "options": {
        "A": "60000",
        "B": "80000",
        "C": "120000",
        "D": "200000"
      },
      "correctAnswer": "C",
      "explanation": "合資格延期年金保費容許夫婦合共申\n請扣除總額上限是12萬",
      "score": 10
    },
    {
      "id": "q21",
      "type": "single",
      "content": "當受保人去世時，賠償會直接向貸款人償還貸款餘額，這是什麼類型的保險？",
      "options": {
        "A": "遞增定期壽險",
        "B": "信用壽險",
        "C": "家庭收入壽險",
        "D": "抵押贖回壽險"
      },
      "correctAnswer": "B",
      "explanation": "如果借款人在未完全償還欠款之前死\n亡，信用壽險直接向貸款人支付貸款\n結欠",
      "score": 10
    },
    {
      "id": "q22",
      "type": "single",
      "content": "丈夫和妻子以聯名形式購買了抵押贖回保險保單，丈夫不幸去世後，賠償金會給付：",
      "options": {
        "A": "妻子",
        "B": "銀行",
        "C": "他們的子女",
        "D": "貸款機構"
      },
      "correctAnswer": "D",
      "explanation": "以聯合壽險方式提供保障的壽險保單\n承保兩人夫婦兩人的生命，\n不論哪一位最先或最後死亡\n，保單於此 時支付保險利益。 A\n23  2.1.1b(a)\n下列哪項對於可續保定期壽險的描述是正確的?\na)在續保時,其保費增加以反映其年齡之提高\nb)在續保時,其保額只可相同或小於其原有保障額\nc)於續保時,無須提供可保性證明\nd)以上所列各項\n以上各項皆是可續保定期壽險可續保\n定期壽險的正確描述",
      "score": 10
    },
    {
      "id": "q25",
      "type": "single",
      "content": "一份不分紅終身壽險：",
      "options": {
        "A": "只會於指定期間結束時才給付保單利益",
        "B": "就不論甚麼時間出現的死亡，均會給付保額",
        "C": "於受保生命仍然在世期間給付指定的利益",
        "D": "只會就指定期間內出現的死亡給付保單利益"
      },
      "correctAnswer": "B",
      "explanation": "一份不分紅終身壽險就不論甚麼時間\n出現的死亡，均會給付保額",
      "score": 10
    },
    {
      "id": "q26",
      "type": "single",
      "content": "一份人壽保險單如稱為「連續繳費終身壽險單」，則意味著:",
      "options": {
        "A": "受保人只需繳付一份保費",
        "B": "在保險期內保費不變",
        "C": "在限定期間受保人在去世後，仍需繳付保費",
        "D": "受保人須終身繳付保費"
      },
      "correctAnswer": "D",
      "explanation": "純粹壽險是指受保生命在世期間終身\n繳付保費，亦可稱為「連續繳費終身\n壽險單，亦是終身壽險的別稱，",
      "score": 10
    },
    {
      "id": "q27",
      "type": "single",
      "content": "下列哪項關於萬用壽險的陳述是不正確的?",
      "options": {
        "A": "具有分別列示各定價因素的定價",
        "B": "保費靈活,可以於某一年完全不繳付保險費",
        "C": "一種非常複雜的產品,它為保單所有人提供極大的自由度",
        "D": "無須要提供可保性證明,可要求增加或減少保險利益"
      },
      "correctAnswer": "D",
      "explanation": "萬用壽險就任何增加保險利益的情況\n都可能須要提供可保性證明",
      "score": 10
    },
    {
      "id": "q28",
      "type": "single",
      "content": "絕大部分的單位相連保單是終身壽險和下列哪種:",
      "options": {
        "A": "定期壽險",
        "B": "儲蓄壽險",
        "C": "純生存壽險",
        "D": "遞減定期壽險"
      },
      "correctAnswer": "B",
      "explanation": "絕大部分的單位相連保單是終身壽險\n和儲蓄壽險",
      "score": 10
    },
    {
      "id": "q29",
      "type": "single",
      "content": "年金利益款項給付予?",
      "options": {
        "A": "收款人",
        "B": "保單受益人",
        "C": "保單持有人",
        "D": "年金購買人"
      },
      "correctAnswer": "A",
      "explanation": "年金利益款項給付予收款人",
      "score": 10
    },
    {
      "id": "q30",
      "type": "single",
      "content": "以下哪項對年金的描述是正確的？",
      "options": {
        "A": "女性不可以購買年金",
        "B": "女性的保費比相同情況下的男性保費為低",
        "C": "向男性支付年金金額低於向女性支付的年金金額",
        "D": "向女性支付年金金額低於向男性支付的年金金額"
      },
      "correctAnswer": "D",
      "explanation": "因為女性的預期壽命比同齡男性長，\n所以向女性支付年金金額低於向男性\n支付的年金金額",
      "score": 10
    },
    {
      "id": "q31",
      "type": "single",
      "content": "一種以整付方式購入，並且於一個年金期間屆滿後便開始支付年金利益款項的年金合約稱為；",
      "options": {
        "A": "即時年金",
        "B": "特快年金",
        "C": "即期年金",
        "D": "連續年金"
      },
      "correctAnswer": "C",
      "explanation": "即期年金是一種以整付方式購入，並\n且於一個年金期間屆滿後便開始支付\n年金利益款項的年金合約",
      "score": 10
    },
    {
      "id": "q32",
      "type": "single",
      "content": "以下哪項有關供款式團體保險計劃是正確的？",
      "options": {
        "A": "僱員無須分擔保費",
        "B": "僱主無須分擔保費",
        "C": "僱主及僱員無須分擔保費",
        "D": "僱主及僱員雙方須分擔保費"
      },
      "correctAnswer": "D",
      "explanation": "供款式團體保險計劃是僱主及僱員雙\n方須分擔保費",
      "score": 10
    },
    {
      "id": "q33",
      "type": "single",
      "content": "就團體人壽保險而言，其中一位合資格被保險人起初拒絕參加保險計劃，後來又想加入，以上的情\n形是？",
      "options": {
        "A": "沒有可能加入",
        "B": "不需任何手續就可加入",
        "C": "只有繳付己過期但未繳清的保費才可",
        "D": "可以加入，但有可能需要出示可保性證明"
      },
      "correctAnswer": "D",
      "explanation": "就團體人壽保險而言，其中一位合資\n格被保險人起初拒絕參加保險計劃，\n後來又想加入，是可以的，但有可能\n需要出示可保性證明",
      "score": 10
    },
    {
      "id": "q3",
      "type": "single",
      "content": ")\n以下哪項是自願醫保計劃下標準計劃靈活計劃中，基本保障，額外保障及其他保障的定義原則?\n1.\t 標準計劃 - 基本保障:必須包括，額外保障:不可包括，其他保障 : (1)\n2.\t 靈活計劃 - 基本保障:必須包括，額外保障: (2)，其他保障 : (3)",
      "options": {
        "A": "(1)不可包括,(2)必須包括,(3)可選擇包括或不包括",
        "B": "(1)必須包括,(2)必須包括,(3)可選擇包括或不包括",
        "C": "(1)可選擇包括或不包括,(2)必須包括,(3)可選擇包括或不包括",
        "D": "(1)可選擇包括或不包括, (2)必須包括, (3)不可包括"
      },
      "correctAnswer": "C",
      "explanation": "詳細可參閱研習資料手冊參考章節\n3.4.1(iii)(7)自願醫保標準計劃和靈\n活計劃定義原則說明表格",
      "score": 10
    },
    {
      "id": "q35",
      "type": "single",
      "content": "附加於人壽保單的意外死亡及喪失肢體附約，有時會賠付超出意外死亡保險利益及其他保險利益，\n以下哪項是適用的保障範圍?\n(i) 嚴重燒傷，可獲支付指明金額\n(ii) 每周津貼，最長為52周\n(iii) 住院津貼，每日津貼上限為 1,000日\n(iv) 因乘搭一般公共交通工具引果傷殘可獲「雙倍賠償」",
      "options": {
        "A": "i,ii",
        "B": "ii,iii",
        "C": "ii,iii,iv",
        "D": "i,ii,iii,iv"
      },
      "correctAnswer": "D",
      "explanation": "以上各項皆是意外死亡保險利益附約\n所提供的其他保險利益",
      "score": 10
    },
    {
      "id": "q36",
      "type": "single",
      "content": "意外死亡及喪失肢體(AD&D)附約，近因原則對這種附約顯得非常重要，原因是:",
      "options": {
        "A": "不適用於危疾保單",
        "B": "只有被保險人因意外死亡才有會給付雙倍賠償利益",
        "C": "每索償賠付，都會是保單基本保單保額的兩倍",
        "D": "就一宗意外而引致的傷殘，喪失肢體利益及死亡保險金同時支付"
      },
      "correctAnswer": "D",
      "explanation": "就意外死亡及喪失肢體(AD&D)附約而\n言，只有被保險人因意外死亡才有會\n給付雙倍賠償利益，所以近因原則(死\n亡原因)對這種附約顯得非常重要 B\n37  3.4.2\n以下哪項屬醫療保險業務指引的目的適用範圍?\na)個人及團體業務\nb)自願醫保認可產品\nc)其他種類醫療保險業務\nd)以上各項皆是\n所有醫療保險業務指引適用於所有醫\n療保險業務",
      "score": 10
    },
    {
      "id": "q38",
      "type": "single",
      "content": "以下哪項不是殘疾收入附約的常用條款?",
      "options": {
        "A": "預期健康狀況",
        "B": "應付金額",
        "C": "等候期",
        "D": "並非貸款或預繳"
      },
      "correctAnswer": "A",
      "explanation": "預期健康狀況不是殘疾收入附約的常\n用條款",
      "score": 10
    },
    {
      "id": "q39",
      "type": "single",
      "content": "以下哪項或哪些有關「豁免保費」附約的支付利益準則描述是正確的？",
      "options": {
        "A": "受保保單所有人在變成完全傷殘時必須維持達到某段時間然後死亡",
        "B": "受保保單所有人在變成完全傷殘時必須已經有部份殘疾達到某段時間",
        "C": "受保保單所有人必須在保單有效期內完全傷殘且達到某段時間, 稱為 「等候期」",
        "D": "以上所有各項均不屬於豁免保費附約支付利益的準則"
      },
      "correctAnswer": "B",
      "explanation": "受保保單所有人一旦根據保單的定義\n完全傷殘達最低期限（通常為三或六\n個月）他將獲豁免支付續保保費。一\n經開始，豁免會於保單的有效期內繼\n續下去，一直到相關傷殘結束為止。 C\n40 3.1.1(a )\n下列那兩項對殘疾豁免保費的描述是不正確的？\ni.從保單所有人遭受到殘疾起計至等候期完結後，保費才開始被豁免\nii.從保單所有人遭受到殘疾之時計起，保費才開始被豁免\niii. 等候期通常是三個月或六個月\niv. 保單所有人的年齡是沒有限制的\na)i 及 ii\nb)ii 及 iv\nc)iii 及 iv\nd)i 及 iv\n豁免一般只限於指明年歲範圍內開始\n的傷殘，比如15至65歲。受保保單所\n有人一旦根據保單的定義完全傷殘達\n最低期限（通常為三或六個月）他將\n獲豁免支付續保保費。選項ii 及\niv不正確",
      "score": 10
    },
    {
      "id": "q41",
      "type": "single",
      "content": "意外死亡保險利益附約支付利益的準則,死亡必須於?",
      "options": {
        "A": "意外身體受傷後一段指定時間內發生",
        "B": "有關基本計劃須包含豁免保費附約",
        "C": "在受保保單所有人昏迷時死亡",
        "D": "即時死亡"
      },
      "correctAnswer": "A",
      "explanation": "意外死亡保險利益附約支付利益的準\n則，死亡必須由意外身體受傷而直接\n引起， 並與所有其他原因無關並\n於該受傷的一年之內發生",
      "score": 10
    },
    {
      "id": "q42",
      "type": "single",
      "content": "根據提前支付死亡保險利益條款，在某些嚴重的情況下，縱使死亡並未發生，保單所列明的死亡金\n是可以支付給保單所有人，但：",
      "options": {
        "A": "受益人/承讓人必須簽署棄權聲明",
        "B": "受益人同樣可以取回所有索償",
        "C": "受益人如果在受保人死後兩年內便可獲取所有索償",
        "D": "受益人只可取回保費"
      },
      "correctAnswer": "A",
      "explanation": "由於向在世的受保保單所有人發放保\n險利益會對保單受益人的期望造成一\n定的影響，因此有些保險人會於處理\n此類附約的給付申請時，要求受益人\n簽署一份棄權聲明或稱解除責任憑證\n，同意提前支付的保險利益數額會從\n將來的死亡保險金中扣除。",
      "score": 10
    },
    {
      "id": "q43",
      "type": "single",
      "content": "以下哪項是危疾保險利益的賠償限制?\ni.\t 被診斷患上指明疾病\nii.\t 被診斷患上終末疾病並只有18個月或更短的壽命\niii.\t 有必要接受指明的醫療程序\niv.\t 僅適用60歲或以下的受保人",
      "options": {
        "A": "i,ii",
        "B": "i,iii",
        "C": "ii,iii,iv",
        "D": "i,iii,iv"
      },
      "correctAnswer": "B",
      "explanation": "危疾保險利益的賠償限制被診斷患上\n終末疾病並只有12個月或更短的壽命\n，危疾保障僅適用於某歲數（如\n80歲）或以下的人，只有選項i,iii是\n正確",
      "score": 10
    },
    {
      "id": "q44",
      "type": "single",
      "content": "自願醫保計劃推動個人住院保險產品的發展，並為香港保險人帶來甚麼機會?",
      "options": {
        "A": "自願醫保容許參與的保險人提供受認可的個人償款住院保險產品，供消費者自願選購",
        "B": "自願醫保容許參與的保險人提供受認可的個人及團體償款住院保險產品，供消費者自願選購",
        "C": "自願醫保容許參與保險人提供受稅務局認可的個人償款住院保險產品，供消費者自願選購",
        "D": "自願醫保容許參與保險人提供受稅務局認可的個人償款住院保險產品，僅供香港居民自由購買"
      },
      "correctAnswer": "A",
      "explanation": "自願醫保容許參與的保險人提供受認\n可的個人償款住院保險產品，供消費\n者自願選購，團體保險並不適用",
      "score": 10
    },
    {
      "id": "q45",
      "type": "single",
      "content": "自願醫保計劃（簡稱「自願醫保」）為保險買家提供了甚麼的機會?",
      "options": {
        "A": "自願醫保為沒有能力承擔私營醫療服務的消費者提供保險計劃",
        "B": "自願醫保為沒有獲僱主提供醫療保險的消費者提供保險計劃",
        "C": "自願醫保為願意及有能力使用私營醫療服務的消費者提額外的保險計劃選擇",
        "D": "自願醫保為沒有能力承擔私營醫療服務的消費者提供保險低收入保險計劃"
      },
      "correctAnswer": "C",
      "explanation": "自願醫保為願意及有能力使用私營醫\n療服務的消費者提額外的保險計劃選\n擇",
      "score": 10
    },
    {
      "id": "q46",
      "type": "single",
      "content": "保證可保利益在某些情況下亦稱為：",
      "options": {
        "A": "終身保證利益",
        "B": "預批購買選擇",
        "C": "終身可保選擇",
        "D": "保證受保利益"
      },
      "correctAnswer": "B",
      "explanation": "保證可保利益在某些情況下亦稱為預\n批購買選擇",
      "score": 10
    },
    {
      "id": "q47",
      "type": "single",
      "content": "以下哪項不是(WP)附約的描述？",
      "options": {
        "A": "(WP)是”waiting period”的縮寫，意指「等候期」",
        "B": "(WP)是”waiver of premium”的縮寫，意指「殘疾豁免保費附約」",
        "C": "被保險保單所有人須要完全傷殘，才可獲權益",
        "D": "受到特定年齡所限制"
      },
      "correctAnswer": "D",
      "explanation": "(WP)是Waiver of\nPremium的縮寫，意指「殘疾豁免保費\n附約」，而不是waiting\nperiod”「等候期」的意思 A\n48  3.1.2\n如果人壽保單收到殘疾收入附約約束,並且受保生命遭遇殘疾,而現正提供收入:\na)該收入通常以每月形式支付\nb)其基本保障會暫時停止\nc)所支付金額會於死亡保障額中扣除\nd)此類保障通常並不設有等候期\n殘疾收入等候期由一個月至六個月不\n等，所支付的利益並非貸款或預繳，\n不會於死亡保障額中扣除，殘疾收入\n附約如名稱所示，則在完全殘疾期間\n提供收入 A\n49  3.1.2\n把「豁免保費附約」及「殘疾收入附約」比較時:\na)兩者皆無分別\nb)豁免保費附約受等候時間所限\nc)豁免保費附約在完全殘疾期間提供一項收入\nd)殘疾保險利益在完全殘疾期間提供一項收入\n把「豁免保費附約」及「殘疾收入附\n約」比較時，殘疾保險利益在完全殘\n疾期間提供一項收入",
      "score": 10
    },
    {
      "id": "q50",
      "type": "single",
      "content": "根據「殘疾收入附約」所支付的收入保險利益:",
      "options": {
        "A": "會從最後的死亡保險金扣除",
        "B": "不會從最後的死亡保險金扣除",
        "C": "會從未來的紅利扣除",
        "D": "實質上是一種利用額外保費償還的貸款"
      },
      "correctAnswer": "B",
      "explanation": "「殘疾收入附約」所支付的收入保險\n利益不是預繳或貸款，不會從最後的\n死亡保險金扣除",
      "score": 10
    },
    {
      "id": "q51",
      "type": "single",
      "content": "根據意外死亡及喪失肢體附約中，「喪失肢體」是指?",
      "options": {
        "A": "嚴格地指喪失雙臂",
        "B": "必須喪失一雙肢體(雙臂或雙腿)",
        "C": "往往適用於單目失明(同時適用於喪失肢體)",
        "D": "可用於雙目失明"
      },
      "correctAnswer": "C",
      "explanation": "在意外死亡及喪失肢體附約中，「喪\n失肢體」包括喪失肢體及喪失視力的\n意思",
      "score": 10
    },
    {
      "id": "q52",
      "type": "single",
      "content": "提前支付死亡權益附約可附加在人壽保險單中，以下哪項描述是正確的？",
      "options": {
        "A": "只適用於分紅保單",
        "B": "只適用於保障額較少的保單",
        "C": "只適用於保障額較大的保單",
        "D": "在是次申請，必須經過第二次體檢"
      },
      "correctAnswer": "C",
      "explanation": "為了降低行政成本，這種附約往往只\n准附加於保額相當大的保單。",
      "score": 10
    },
    {
      "id": "q53",
      "type": "single",
      "content": "危疾保險利益中\"指明疾病\"指:\ni. 傷殘\nii. 心臟相關疾病\niii.癌症\niv. 重要器官相關疾病",
      "options": {
        "A": "i,ii, iii",
        "B": "ii,iii, iv",
        "C": "i,ii, iv",
        "D": "i,ii,iii ,iv"
      },
      "correctAnswer": "D",
      "explanation": "以上都可以是危疾保險利益中\"指明疾\n病\"",
      "score": 10
    },
    {
      "id": "q54",
      "type": "single",
      "content": "有關保證可保選擇，容許受保人作出購買增額保障的選擇，以下那項描述是不正確的?",
      "options": {
        "A": "自動獲得增額保障的選擇",
        "B": "如不及時作出選擇，便會喪失權利",
        "C": "部分保險人於備擇日期內提供定期壽險",
        "D": "只可在指定限期內作出選擇"
      },
      "correctAnswer": "A",
      "explanation": "保單所有人如果錯過了行使已觸發的\n選擇權以購買增額保障的話，就會喪\n失該次權利，答案A不正確",
      "score": 10
    },
    {
      "id": "q55",
      "type": "single",
      "content": "保證可保利益：",
      "options": {
        "A": "保單所有人有權在指定的備擇日期購買增額保險",
        "B": "備擇日期沒有作出購買增額保障的選擇，就會喪失該項約定的權利",
        "C": "增額保險的金額不能超過原有保單的面額",
        "D": "以上各項皆是"
      },
      "correctAnswer": "D",
      "explanation": "以上各項皆是保證可保利益的限制",
      "score": 10
    },
    {
      "id": "q56",
      "type": "single",
      "content": "如保險已加有豁免保費及預批購買選擇附約，而保單所有人在可以行使購買權時發現遭致傷殘，在\n此情況下，下列哪項為正確？",
      "options": {
        "A": "預批購買選擇會被取消",
        "B": "豁免保費附約會被取消",
        "C": "豁免保費及保證可保利益附約會被取消",
        "D": "可自動獲得該額外保障，豁免保費附約也可以豁免所有保費"
      },
      "correctAnswer": "D",
      "explanation": "受保保單所有人在有權行使購買增額\n保險選擇權時已經成了殘疾人，他將\n會自動獲得該項額外保障。並豁免保\n費，直至受保保單所有人康復或死亡",
      "score": 10
    },
    {
      "id": "q57",
      "type": "single",
      "content": "對於一個保單所有人來說，對保險合約的權益也可形容為「復歸的」 ，即是說:",
      "options": {
        "A": "仍未取得該項權益",
        "B": "肯定會在將來取得該權益",
        "C": "保單所有人對該合約的權益獲得承認，但他尚未能實際享用該項權益",
        "D": "該權益可以轉讓給其他人"
      },
      "correctAnswer": "C",
      "explanation": "「復歸的」權益是指保單所有人對該\n合約的權益獲得承認，但他尚未能實\n際享用該項權益",
      "score": 10
    },
    {
      "id": "q58",
      "type": "single",
      "content": "以下哪項不屬於人壽保險的不能作廢條款，保單的持有人可以作出的選擇?",
      "options": {
        "A": "中止保單時獲付退保現金價值",
        "B": "取回已經支付的保費",
        "C": "利用淨現金價值作為整付保費購買減額清繳保險",
        "D": "以上各項皆不是"
      },
      "correctAnswer": "B",
      "explanation": "取回已經支付的保費不屬於人壽保險\n的不能作廢條款下的選擇",
      "score": 10
    },
    {
      "id": "q59",
      "type": "single",
      "content": "如果具有現金價值或紅利價值的保單的持有人決定不再繳付任何保費，他有權選取：",
      "options": {
        "A": "中止保單時獲付退保現金價值",
        "B": "利用淨現金價值作為整付保費，購買與原保單所提供的計劃相同的但保額較低的人壽保險",
        "C": "A&B",
        "D": "以上皆不是"
      },
      "correctAnswer": "C",
      "explanation": "退保及清繳保險是具有現金價值的保\n單，保單的持有人決定不再繳付任何\n保費有權選取的選擇",
      "score": 10
    },
    {
      "id": "q60",
      "type": "single",
      "content": "下列哪項或哪些不屬於壽險保單的賠付選擇？",
      "options": {
        "A": "保險人有權選擇賠付方法",
        "B": "通常是整筆過支付",
        "C": "用利益購買年金",
        "D": "將收益保留在保險人處以賺取利息"
      },
      "correctAnswer": "A",
      "explanation": "只有保單持有人或受益人有權選擇賠\n付方法，答案A不屬於壽險保單的賠付\n選擇",
      "score": 10
    },
    {
      "id": "q61",
      "type": "single",
      "content": "就誤報年齡或性別方面，人壽保險單通常：",
      "options": {
        "A": "也適用於自願變性的情況",
        "B": "只容許保單利益向上調整",
        "C": "只容許保單利益向下調整",
        "D": "試圖改變保單條款至以符合應有情況"
      },
      "correctAnswer": "D",
      "explanation": "若事實與安排保險時所說明的年齡或\n性別不相同，這可能對保費及／或保\n險利益產生顯著影響。",
      "score": 10
    },
    {
      "id": "q62",
      "type": "single",
      "content": "以下哪項關於「完整合約」條款的描述是正確的？",
      "options": {
        "A": "在人壽保險索償時毋需出示保單的正本",
        "B": "除非得到保單所有人的同意，否則 不能對保險合約作出任何修改",
        "C": "保險公司的指定高級職員有權對保單作出更改",
        "D": "保單的內容已是一份完整的合約，並不包括其他文件"
      },
      "correctAnswer": "B",
      "explanation": "「完整合約」條款其中一個定義是，\n除非得到保單所有人的同意，否則 不\n能對保險合約作出任何修改",
      "score": 10
    },
    {
      "id": "q63",
      "type": "single",
      "content": "黃生就自身生命購買壽險保單，自己為受保人，並指明他最小的兒子為該保單受益人，根據《已婚\n者地位條例》，此舉起了甚麼的法律效用?",
      "options": {
        "A": "該受益人成為該保單的法定保單所有人",
        "B": "該受益人成為該保單的法定保單所有人，直至黃先生修訂其他受益人為止",
        "C": "信託效用並不用適指定子女成為受益人",
        "D": "該受益人成為該保單的實益擁有人"
      },
      "correctAnswer": "B",
      "explanation": "根據《已婚者地位條例》，保單持有\n人如為其配偶及或其任何子女的利益\n而購買壽險單，將達到建立一個（法\n定信託的效用，從而令該配偶及或子\n女成為該保單的實益擁有人。 D\n64  4.5\n以下哪項是不能作廢條款的常規規定?\na)保單所有人可中止保單時獲付退保現金價值\nb)保單不會因為中斷繳付保費而失效，除非收到相反指示，否則保單的現金價值會被用作支付到期\n保費直至用完為止\nc)利用淨現金價值作為整付保費，購買與原保額相同的定期壽險\nd)利用淨現金價值作為整付保費，購買與原保單所提供的計劃相同的但保額較低的人壽保險\n常規的不能作廢條款則規定是保單不\n會因為中斷繳付保費而失效。除非收\n到相反指示，否則保單的現金價值會\n被用作支付到期保費直至用完為止，\n以保持保單全額有效。 B\n65  4.7\n若要把已失效的人壽保單復效，以下哪項不是復效條件?\na)繳一筆復效費\nb)保險人書面同意\nc)繳付已到期而未繳清的保費及利息\nd)提供可保性證明\n保險人書面同意不是人壽保單復效條\n件",
      "score": 10
    },
    {
      "id": "q66",
      "type": "single",
      "content": "以下哪項法律條文容許藉訂明手續來轉讓據法權產?",
      "options": {
        "A": "法律改革(綜合)條例",
        "B": "衡平法的原則",
        "C": "轉讓(據法權產)條例",
        "D": "法律修訂及改革(綜合)條例"
      },
      "correctAnswer": "D",
      "explanation": "《法律修訂及改革(綜合)條例》容許\n藉訂明手續來轉讓據法權產",
      "score": 10
    },
    {
      "id": "q67",
      "type": "single",
      "content": "對保單權益屬轉讓需通過以下甚麼條件才可進行轉讓?",
      "options": {
        "A": "該項權益無論於一般保險或人壽保險單都屬復歸權益",
        "B": "該項權益須屬現時的",
        "C": "該項權益須透過訂明手續來轉讓據法權產",
        "D": "該項權益屬轉屬轉讓人的可保權益"
      },
      "correctAnswer": "B",
      "explanation": "有效的法定轉讓其中的一項標準是，\n擬轉讓的據法權產須屬現時的，而非\n未來的",
      "score": 10
    },
    {
      "id": "q68",
      "type": "single",
      "content": "對保單權益屬轉讓需通過以下甚麼條件才可進行轉讓?",
      "options": {
        "A": "該項權益須透過訂明手續來轉讓據法權產",
        "B": "該項權益須屬於轉讓據法權產",
        "C": "該項權益屬轉屬轉讓人的可保權益",
        "D": "擬轉讓的據法權產須屬現時的，延遲的或未來的"
      },
      "correctAnswer": "B",
      "explanation": "《法律修訂及改革(綜合)條例》容許\n藉訂明手續來轉讓據法權產，而對保\n險合約的權益屬於據法權產。",
      "score": 10
    },
    {
      "id": "q69",
      "type": "single",
      "content": "對於一個保單所有人來說，如果他對產權的權益是復歸的，那：",
      "options": {
        "A": "仍未取得該項權益",
        "B": "雖然對產權有獲得認可的權益，財產的享用將延遲至將來的某一天或某事發生時",
        "C": "肯定會在將來取得該權益",
        "D": "該權益屬於受益人權益"
      },
      "correctAnswer": "B",
      "explanation": "復歸的權益是指對產權有獲得認可的\n權益，財產的享用將延遲至將來的某\n一天或某事發生時",
      "score": 10
    },
    {
      "id": "q70",
      "type": "single",
      "content": "按照香港普遍採用的「不可異議條款」，儘管違反「最高誠信原則」(假設按照香港法律)，保險人\n對以下哪項仍不可能拒絕有關之死亡索償？",
      "options": {
        "A": "保單生效了只有一年",
        "B": "保單生效了20個月,但死亡6個月後才向保險人索償",
        "C": "保單生效了4年，違反最高誠信原則涉及故意隱瞞有重要意義的的醫療資料",
        "D": "保單生效了4年，違反最高誠信原則涉及到沒有披露重要資料，而投保人真誠地認為此資料是無"
      },
      "correctAnswer": "C",
      "explanation": "關的\n不可異議條款規定，保險合約於受保\n生命在世時從保單發出日起計已生效\n了兩年後，保險人不會對該合約提出\n異議或質疑，答案D的情況保險人仍不\n可能拒絕有關之死亡索償 D\n試卷三: ⾧期保險 —2025年12月份每月精選試題\n71  4.2\n不可異議條款規定保險人不能對保單有效性提出異議，該可異議期為：\na)十二個月\nb)三個月\nc)二年\nd)一個月\n不可異議條款規定保險人不能對保單\n有效性提出異議，該可異議期為兩年",
      "score": 10
    },
    {
      "id": "q72",
      "type": "single",
      "content": "下列哪項或哪些有關寬限期條款的陳述是不正確的？",
      "options": {
        "A": "該期間一般最少30或31天",
        "B": "它不適用於保單的首期保費",
        "C": "於寬限期內繳付保費可維持保單的保障繼續有效",
        "D": "於寬限期內繳付保費須另外繳付利息"
      },
      "correctAnswer": "D",
      "explanation": "於寬限期內繳付保費須被視為準時繳\n交",
      "score": 10
    },
    {
      "id": "q73",
      "type": "single",
      "content": "根據壽險保單中常見的不能作廢條例，下列哪一項不屬於決定不再繳付任何保費的保單所有人的選\n擇?",
      "options": {
        "A": "退保並收取保單現金價值",
        "B": "利用保單價值作為保費，接受一份減額清繳保險",
        "C": "利用現金價值購買與原本保單保額相同的定額壽險",
        "D": "暫停保障，但有權在任何時間恢復保險"
      },
      "correctAnswer": "D",
      "explanation": "暫停保障，但有權在任何時間恢復保\n險不屬於決定不再繳付任何保費的保\n單所有人的選擇",
      "score": 10
    },
    {
      "id": "q74",
      "type": "single",
      "content": "如果抵押貸款在投保生命死亡時仍未清還，那麼:",
      "options": {
        "A": "有關的死亡索償便會無效",
        "B": "有關的保險人可豁免該筆保費的償還",
        "C": "受益人於支付該保險利益前,要先繳清該筆貸款",
        "D": "有關的抵押貸款及相關的利息會在保單利益中扣減"
      },
      "correctAnswer": "D",
      "explanation": "如果抵押貸款在投保生命死亡時仍未\n清還，有關的抵押貸款及相關的利息\n會在保單利益中扣減",
      "score": 10
    },
    {
      "id": "q75",
      "type": "single",
      "content": "下列哪項屬於保單抵押貸款中不大可能是正確的?",
      "options": {
        "A": "該筆貸款用途無任何限制",
        "B": "該筆貸款唯一需要的抵押品就是保單的現金價值",
        "C": "若是意外死亡，不須償還該筆貸款",
        "D": "貸款金額須在受保生命死亡時在保額內扣除"
      },
      "correctAnswer": "C",
      "explanation": "保單抵押貸款貸款金額須在受保生命\n死亡時在保額內扣除，不論任何原因\n身故，答案C不正確。",
      "score": 10
    },
    {
      "id": "q76",
      "type": "single",
      "content": "如果保單於提出索償時，才發現有關受保生命的真實年齡較保單顯示的為高：",
      "options": {
        "A": "保單自動無效",
        "B": "調整利益，支付比保單較低的保額",
        "C": "調整利益，支付比保單較高的保額",
        "D": "維持保額不變，退回多繳的保費"
      },
      "correctAnswer": "C",
      "explanation": "如果保單於提出索償時，才發現有關\n受保生命的真實年齡較保單顯示的為\n高，即是出現少交保費的情況，保險\n人會調整利益，支付比保單較低的保\n額 B\n77  4.10\n如保單所有人沒有註明紅利的選擇，保險人會自動為保單所有人將紅利存放以賺取利息或：\na)以現金支付\nb)用以繳付未來保費\nc)用以購買清繳增額保險\nd)購買一年期的定期壽險\n購買清繳增額保險及紅利存放保險人\n以賺取利息屬自動紅利選擇",
      "score": 10
    },
    {
      "id": "q78",
      "type": "single",
      "content": "下列哪項或哪些屬於壽險保單的賠付選擇？",
      "options": {
        "A": "即時整筆支付",
        "B": "受益人逝世時整筆支付",
        "C": "投資於有關保險公司的股份",
        "D": "以上所有各項"
      },
      "correctAnswer": "A",
      "explanation": "上述只有即時整筆支付死亡保險利益\n屬於壽險保單的賠付選擇",
      "score": 10
    },
    {
      "id": "q79",
      "type": "single",
      "content": "在理賠時，下列那種方法不是常用的？",
      "options": {
        "A": "整筆支付",
        "B": "以定期定額支付",
        "C": "定額支付",
        "D": "以有關公司的股份支付"
      },
      "correctAnswer": "D",
      "explanation": "以有關公司的股份支付不是常用的理\n賠選擇",
      "score": 10
    },
    {
      "id": "q80",
      "type": "single",
      "content": "壽險保單中的自殺條款目的在於?",
      "options": {
        "A": "阻止人們自殺",
        "B": "把所有涉及自殺的索償無效",
        "C": "避免本著自殺的念頭而購買的人壽保險生效",
        "D": "杜絕所有涉及自殺的索償的可能性"
      },
      "correctAnswer": "C",
      "explanation": "自殺除外責任條款是為防止有人藉自\n殺來取得保險金賠償，保險人採取一\n些防範措施，也絕對是合理的。",
      "score": 10
    },
    {
      "id": "q81",
      "type": "single",
      "content": "下面有關宣佈紅利金額的陳述中，哪項是正確的？\ni.\t 保險人一般會將紅利平均派發，以減低短期大幅波動\nii.\t 紅利金額是基於獲委任精算師的意見\niii.\t 紅利金額是基於獲委任財務總裁的意見，並經精算師批准而釐定\niv.\t 保險人一般保留釐定紅利金額的權利",
      "options": {
        "A": "i,ii",
        "B": "ii,iii,iv",
        "C": "i,ii,iv",
        "D": "ii,iii"
      },
      "correctAnswer": "C",
      "explanation": "紅利派發金額視乎匯集基金的業績情\n況而定，保險人一般保留釐定紅利金\n額的權利。實務上，紅利金額是基於\n獲委任精算師的意見，並經各董事會\n批准而釐定的。選項iii不正確，正確\n答案是C C\n82  5.2.10\n以下哪項不屬《重要資料聲明書－內地人士在港投購人身╱壽險保單》涵蓋的部分?\na)提前提取保單費用\nb)提前退保費用\nc)紅利\nd)冷靜期\n參考章節5.2.10&附件M\t 冷靜期不屬《\n重要資料聲明書－內地人士在港投購\n人身╱壽險保單》涵蓋的部分，詳細\n研集資料手冊附件M D\n83  5.2.1(b)\n以下哪項是處理人壽險保投保時是應注意的事項？\ni)   下一個(或上一個)生日年齡\nii)  投保人的身份\niii) 保單生效日期\niv)  投保人過去三年的職業紀錄\na)i, iii\nb)ii, iii\nc)i,ii,iii\nd)i,ii, iii, iv\n投保人過去三年的職業不是處理人壽\n險保投保時是應注意的事項，選項iv\n不正確，正確答案是C。",
      "score": 10
    },
    {
      "id": "q84",
      "type": "single",
      "content": "按照指引16的規定，銷售分紅（或有利潤）保單或萬用壽險保單的保險人，應披露每個近期曾發出\n新保單的產品實現率是怎樣計算的?",
      "options": {
        "A": "實現率是指按「實際派發的保證英式紅利」除以銷售時「利益說明所承諾數額」的平均數計算",
        "B": "實現率是指按「實際派發英式紅利」除以銷售時「利益說明所述數額」的平均數計算。",
        "C": "實現率是指按「實際派發的非保證英式紅利」除以銷售時「利益說明所述數額」的平均數計算",
        "D": "實現率是指按「實際派發的英式紅利」除以銷售時「利益說明所承諾數額」的平均數計算"
      },
      "correctAnswer": "C",
      "explanation": "某個產品的實現率是指按「實際派發\n的非保證紅利／英式紅利」除以銷售\n時「利益說明所述數額」的平均數計\n算",
      "score": 10
    },
    {
      "id": "q85",
      "type": "single",
      "content": "以下哪項是一項法律原則容許法庭對有損害公眾利益或公共秩序的傾向的行為或交易，可予以廢除\n或不接受?",
      "options": {
        "A": "程序不當",
        "B": "政策公正",
        "C": "公共政策",
        "D": "以上各項皆不是"
      },
      "correctAnswer": "C",
      "explanation": "在大部分情況下，如果證實殺人犯是\n受益人的話，法律\n「公共政策」是不會容許殺人犯本人\n獲益的",
      "score": 10
    },
    {
      "id": "q87",
      "type": "single",
      "content": "保險公司會計部的主要職能和責任包括：\ni)   記錄公司收入\nii)  監管公司支出\niii) 遵守(保費守則)\niv)  遵守(保險代理操守守則)",
      "options": {
        "A": "i, ii",
        "B": "i, iii",
        "C": "iii,iv",
        "D": "ii,iii"
      },
      "correctAnswer": "A",
      "explanation": "遵守(保費守則)及遵守(保險代理操守\n守則)不屬保險公司會計部的職責，選\n項iii&iv不正確",
      "score": 10
    },
    {
      "id": "q88",
      "type": "single",
      "content": "《承保長期保險業務(類別C業務除外)指引》根據以下哪項/些機構頒布的保險核心原則而制定？",
      "options": {
        "A": "國際保險監督聯會",
        "B": "特區政府",
        "C": "保險監督聯合會",
        "D": "國際保險業聯會及國際保險監督聯會"
      },
      "correctAnswer": "A",
      "explanation": "《承保長期保險業務(類別C業務除外)\n指引》根據國際保險監督聯會頒布的\n保險核心原則而制定",
      "score": 10
    },
    {
      "id": "q89",
      "type": "single",
      "content": "下面有關宣佈紅利金額的陳述中，哪項是正確的？\ni.通貨膨脹期間保險人只會派發最低額的紅利\nii. 保險人一般保留釐定紅利金額的權利\niii.紅利金額是基於獲委任精算師的意見，並經董事會批准而釐定\niv.傳統分紅保單規定了上升的紅利率",
      "options": {
        "A": "i , ii",
        "B": "ii, iii",
        "C": "ii,iv",
        "D": "i,ii,iii,iv"
      },
      "correctAnswer": "B",
      "explanation": "保險人一般保留釐定紅利金額的權利\n。紅利金額是基於各自的獲委任精算\n師的意見，並經各自的董事會批准而\n釐定的。只有選項ii,iii正確",
      "score": 10
    },
    {
      "id": "q90",
      "type": "single",
      "content": "以下哪項保險種類會提供「保險憑證」及「成員登記卡」？",
      "options": {
        "A": "終身保險",
        "B": "儲蓄保險",
        "C": "團體保險",
        "D": "以上皆不是"
      },
      "correctAnswer": "C",
      "explanation": "團體保單文件涉及總保單，\n為每位受保人提供保險憑證\n，還有成員登記卡。",
      "score": 10
    },
    {
      "id": "q91",
      "type": "single",
      "content": "下列哪項不大可能屬於保單所有人服務部的職能？",
      "options": {
        "A": "通訊",
        "B": "收取保費",
        "C": "索償處理",
        "D": "權益管理"
      },
      "correctAnswer": "C",
      "explanation": "索償處理屬理賠部負責",
      "score": 10
    },
    {
      "id": "q92",
      "type": "single",
      "content": "人壽保險人透過簽發其中一種的保費收據，表示同意有關保險於投保時開始生效，但須於稍後證實\n投保人按照標準條款是屬於可保的。這種收據稱為：",
      "options": {
        "A": "暫時性保費收據",
        "B": "立約保費收據",
        "C": "附條件保費收據",
        "D": "臨時性保費收據"
      },
      "correctAnswer": "C",
      "explanation": "附條件保費收據須於稍後證實投保人\n按照標準條款是屬於可保的，有關保\n險於投保時開始生效",
      "score": 10
    },
    {
      "id": "q93",
      "type": "single",
      "content": "立約保費收據有另一名稱，其中TIA全名為：",
      "options": {
        "A": "定期被接納保險 Term Insurance accepted",
        "B": "臨時保險證明 Temporary Insurance acknowledge",
        "C": "臨時保險協議 Temporary Insurance agreement",
        "D": "定期保險申請 Term Insurance application"
      },
      "correctAnswer": "C",
      "explanation": "立約保費收據有另一名稱，其中TIA全\n名為臨時保險協議 Temporary\nInsurance agreement",
      "score": 10
    },
    {
      "id": "q94",
      "type": "single",
      "content": "黃先生現年五十五歲，計劃六十歲退休，他請你提供壽險和投資上的意見，你覺得投資相連長期保\n險適合他嗎？",
      "options": {
        "A": "需要視乎他的目標及適合情況，這是他可以選擇的選項",
        "B": "投資風險對他來說屬於相當高，故不建議投資相連長期保險給他",
        "C": "以他的年齡來說，傳統壽險會較適合",
        "D": "不建議投資相連保險，因為它是靈活性不適合一位五十五歲的人士"
      },
      "correctAnswer": "A",
      "explanation": "持牌保險中介人就任何合適的人壽保\n險保單作出建議前，須確保對各客戶\n的情況，包括需要、財務狀況、支付\n保費的能力及意願等作適當評估，及\n所作出的建議是建基於該評估，答案A\n正確",
      "score": 10
    },
    {
      "id": "q95",
      "type": "single",
      "content": "以下哪項或哪些說明是正確?",
      "options": {
        "A": "壽險的核保工作是每個保單年度必須的工作",
        "B": "壽險的核保工作只涉及有關保費",
        "C": "核保涉及可保性和合約條款的修改",
        "D": "以上各項皆是"
      },
      "correctAnswer": "C",
      "explanation": "核保涉及可保性和合約條款的修改，\n通常人壽保險對個別風險的核保只能\n進行一次，只有答案C正確",
      "score": 10
    },
    {
      "id": "q96",
      "type": "single",
      "content": "核保包括兩類型。其一是技術性核保，這是將個別風險的潛在危機及預期危險進行評估。另一類是\n計算就同一受保生命已累積購買的保單金額及對建議的保險金額作出評估，此類核保稱為：",
      "options": {
        "A": "標準核保",
        "B": "實際風險核保",
        "C": "財務性核保",
        "D": "全面性核保"
      },
      "correctAnswer": "C",
      "explanation": "計算就同一受保生命已累積購買的保\n單金額及對建議的保險金額作出評估\n，此類核保稱為財務性核保",
      "score": 10
    },
    {
      "id": "q97",
      "type": "single",
      "content": "有時候合資格醫務人員所有的資料要進一步調查，保險公司除了向主診醫生索取醫療資料外，還可\n以向哪位索取：",
      "options": {
        "A": "護理醫生",
        "B": "體檢醫生",
        "C": "保險公司指明醫生",
        "D": "非主診醫生"
      },
      "correctAnswer": "B",
      "explanation": "有時候合資格醫務人員所提供的進一\n步資料是有必要的。這類調查的來源\n可以是主診醫生或體檢醫生",
      "score": 10
    },
    {
      "id": "q98",
      "type": "single",
      "content": "以下哪項或哪些原因需要主診醫生的醫療報告?",
      "options": {
        "A": "所要求的保額十分高",
        "B": "已超過某指明的年齡",
        "C": "就投保書上所披露的某些健康資料作進一步調查",
        "D": "以上各項皆是"
      },
      "correctAnswer": "D",
      "explanation": "以上各項皆是需要主診醫生的醫療報\n告",
      "score": 10
    },
    {
      "id": "q99",
      "type": "single",
      "content": "就死亡索償提出時，死亡證明方式為：",
      "options": {
        "A": "死亡證明書正本",
        "B": "死亡證明書副本",
        "C": "受益人簽署證明",
        "D": "以上任何一項"
      },
      "correctAnswer": "A",
      "explanation": "就死亡索償提出時，死亡證明方式為\n死亡證明書正本",
      "score": 10
    },
    {
      "id": "q5",
      "type": "single",
      "content": ")\n如果一名客戶暗示，他正在考慮將本身的保單退保，保險中介人應採取以下哪項或哪些行動？",
      "options": {
        "A": "有禮地詢問為何作出這個決定",
        "B": "小心地解釋保單退保的權利或影響",
        "C": "略述各種其他的可能選擇(如保單抵押貸款，清繳保障等)",
        "D": "以上各項皆是"
      },
      "correctAnswer": "D",
      "explanation": "以上各項皆是保險中介人處理保單退\n保時應採取的行動",
      "score": 10
    }
  ]
}